package/__init__.py
package/module.py
martstelm_DE2v2.1.5-0.1.1.dist-info/METADATA
martstelm_DE2v2.1.5-0.1.1.dist-info/WHEEL
martstelm_DE2v2.1.5-0.1.1.dist-info/top_level.txt
martstelm_DE2v2.1.5-0.1.1.dist-info/RECORD
